[
    {
        "name": "Handcrafted Wooden Bowl",
        "price": "35.99",
        "craftsman": "Emma Thompson",
        "location": "Aspen, USA",
        "imageUrl": "./assets/wooden bowl.png"
       
    },
    {
        "name": "Organic Cotton Scarf",
        "price": "24.50",
        "craftsman": "Olivia Lee",
        "location": "Brighton, UK",
        "imageUrl": "./assets/organic-cotton-scarf.png"
       
       
    
        

       
    },
    {
        "name": "Ceramic Coffee Mug",
        "price": "18.00",
        "craftsman" : "Jack Martin",
        "location": "Melbourne,Australia",
        "imageUrl": "./assets/ceramic-coffee-mug.png"
       
        
    },
     
    {
        
        "name": "Bambo Serving Tray",
        "price": "29.99",
        "craftsman" : "Sophia Garcia",
        "location": "Barcelona,Spain",
        "imageUrl": "./assets/bamboo-serving-tray.png"
        
    
    },
    {
        
        "name": "Hand-Dyed Silk Scarves",
        "price": "60.00",
        "craftsman" : "Harper Rvans",
        "location": "Kyoto,Japan",
        "imageUrl": "./assets/hand-dyed-silk-scarves.png"
        
    },
    {
        
        "name": "Recycled Glass Vase",
        "price": "42.75",
        "craftsman" : "Daniel Kim",
        "location": "Seoul,South Korea",
        "imageUrl": "./assets/recycled-glass-vase.png"
    },
       
    {
        
        "name": "Leather Journal",
        "price": "29.99",
        "craftsman" : "Liam Patel",
        "location": "Mumbai,India",
        "imageUrl": "./assets/leather-journal.png"
       
    },
    {
        
        "name": "Wool Knit Hat",
        "price": "19.99",
        "craftsman" : "Amelia Baker",
        "location": "Dublin,Ireland",
        "imageUrl": "./assets/wool-knit-hat.png"
       
    },
    {
        
        "name": "Handmade Soup Set",
        "price": "16.50",
        "craftsman" : "Ava Robinson",
        "location": "Portland,USA",
        "imageUrl": "./assets/handmade-soup-set.png"
      
    },
    {
        
        "name": "Upcycled Denim Bag",
        "price": "37.80",
        "craftsman" : "James Brown",
        "location": "London,UK",
        "imageUrl": "./assets/upcycled-denim-bag.png"
        
    },
    {
        
        "name": "Clay Pendant Necklace",
        "price": "27.99",
        "craftsman" : "Sophia Harris",
        "location": "Sydney,Australia",
        "imageUrl": "./assets/clay-pendant-necklace.png"
      
    },
    {
        
        "name": "Wooden Puzzle Game",
        "price": "14.99",
        "craftsman" : "Benjamin Clark",
        "location": "Berlin,Germany",
        "imageUrl": "./assets/wooden-puzzle-game.png"
        
    }
]


